setup.py
distributions_ndh/Binomialdistribution.py
distributions_ndh/Gaussiandistribution.py
distributions_ndh/Generaldistribution.py
distributions_ndh/__init__.py
distributions_ndh.egg-info/PKG-INFO
distributions_ndh.egg-info/SOURCES.txt
distributions_ndh.egg-info/dependency_links.txt
distributions_ndh.egg-info/not-zip-safe
distributions_ndh.egg-info/top_level.txt